expyriment/__init__.py
expyriment/__main__.py
expyriment/_api_reference_tool.py
expyriment/_internals.py
expyriment/cli.py
expyriment/expyriment_logo.png
expyriment/xpy_icon.png
expyriment/_fonts/AUTHORS
expyriment/_fonts/COPYING
expyriment/_fonts/CREDITS
expyriment/_fonts/ChangeLog
expyriment/_fonts/FreeMono.ttf
expyriment/_fonts/FreeMonoBold.ttf
expyriment/_fonts/FreeMonoBoldOblique.ttf
expyriment/_fonts/FreeMonoOblique.ttf
expyriment/_fonts/FreeSans.ttf
expyriment/_fonts/FreeSansBold.ttf
expyriment/_fonts/FreeSansBoldOblique.ttf
expyriment/_fonts/FreeSansOblique.ttf
expyriment/_fonts/FreeSerif.ttf
expyriment/_fonts/FreeSerifBold.ttf
expyriment/_fonts/FreeSerifBoldItalic.ttf
expyriment/_fonts/FreeSerifItalic.ttf
expyriment/_fonts/INSTALL
expyriment/_fonts/README
expyriment/_fonts/TROUBLESHOOTING
expyriment/_fonts/USAGE
expyriment/control/__init__.py
expyriment/control/_experiment_control.py
expyriment/control/_miscellaneous.py
expyriment/control/_test_suite.py
expyriment/control/defaults.py
expyriment/design/__init__.py
expyriment/design/_structure.py
expyriment/design/defaults.py
expyriment/design/randomize.py
expyriment/design/extras/__init__.py
expyriment/design/permute/__init__.py
expyriment/design/permute/_permute.py
expyriment/design/randomise/__init__.py
expyriment/design/randomise/_randomise.py
expyriment/io/__init__.py
expyriment/io/_eventbuttonbox.py
expyriment/io/_files.py
expyriment/io/_gamepad.py
expyriment/io/_input_output.py
expyriment/io/_keyboard.py
expyriment/io/_markeroutput.py
expyriment/io/_mouse.py
expyriment/io/_screen.py
expyriment/io/_serialport.py
expyriment/io/_streamingbuttonbox.py
expyriment/io/_textinput.py
expyriment/io/_textmenu.py
expyriment/io/_touchscreenbuttonbox.py
expyriment/io/_triggerinput.py
expyriment/io/defaults.py
expyriment/io/_parallelport/__init__.py
expyriment/io/_parallelport/_dlportio.py
expyriment/io/_parallelport/_inpout32.py
expyriment/io/_parallelport/_linux.py
expyriment/io/extras/__init__.py
expyriment-1.0.0.dist-info/entry_points.txt
expyriment-1.0.0.dist-info/licenses/COPYING.txt
expyriment-1.0.0.dist-info/WHEEL
expyriment-1.0.0.dist-info/METADATA
expyriment-1.0.0.dist-info/RECORD
