Metadata-Version: 2.4
Name: expyriment
Version: 1.0.0
Summary: A Python library for cognitive and neuroscientific experiments
Keywords: experiment control,open science,neuroscience,experimental psychology
Author-email: Florian Krause <florian@expyriment.org>, Oliver Lindemann <oliver@expyriment.org>
Requires-Python: >=3.10
License-Expression: GPL-3.0-or-later
Classifier: Intended Audience :: Science/Research
Classifier: Topic :: Software Development :: Libraries :: Python Modules
Classifier: Programming Language :: Python :: 3
Classifier: Operating System :: OS Independent
License-File: COPYING.txt
Requires-Dist: pygame>=2.5.2,<3
Requires-Dist: pyopengl>=3,<4
Requires-Dist: numpy>=1.6,<3
Requires-Dist: pyserial>=3,<4
Requires-Dist: pyparallel>=0.2,<1; sys_platform == 'linux'
Requires-Dist: mediadecoder>=0.2.3,<1
Project-URL: Bug Tracker, https://github.com/expyriment/expyriment/issues
Project-URL: Documentation, https://docs.expyriment.org/
Project-URL: Homepage, https://expyriment.org/
